geojnu/__init__.py
geojnu/common.py
geojnu/geojnu.py
geojnu-0.0.2.dist-info/licenses/LICENSE
geojnu-0.0.2.dist-info/METADATA
geojnu-0.0.2.dist-info/WHEEL
geojnu-0.0.2.dist-info/entry_points.txt
geojnu-0.0.2.dist-info/top_level.txt
geojnu-0.0.2.dist-info/RECORD
