Metadata-Version: 2.4
Name: geojnu
Version: 0.0.2
Summary: My First Python Package
Author-email: Alok Kumar <cktdupalokkumar@gmail.com>
License: MIT License
Project-URL: Homepage, https://github.com/alokjnu/geojnu
Keywords: geojnu
Classifier: Intended Audience :: Developers
Classifier: License :: OSI Approved :: MIT License
Classifier: Natural Language :: English
Classifier: Programming Language :: Python :: 3.8
Classifier: Programming Language :: Python :: 3.9
Classifier: Programming Language :: Python :: 3.10
Classifier: Programming Language :: Python :: 3.11
Classifier: Programming Language :: Python :: 3.12
Requires-Python: >=3.8
License-File: LICENSE
Requires-Dist: numpy
Provides-Extra: all
Requires-Dist: geojnu[extra]; extra == "all"
Provides-Extra: extra
Requires-Dist: pandas; extra == "extra"
Dynamic: license-file
